{
  "beers": [
    {
      "name": "11° WitWit",
      "description": "5% alc. piv. Vik, Praha, Witbier"
    },
    {
      "name": "12° Just three Fingers",
      "description": "4,7% alc. piv. Crazy Clown, Praha, Sour Ale s Bezinkou, Fíky a Datlemi"
    },
    {
      "name": "12° PP (Pořádné Pivo)",
      "description": "4,9% alc. piv. JungBerg, Hořice, světlý ležák"
    },
    {
      "name": "12° Pozitron",
      "description": "5% alc. piv. Volt, Jablonec nad Nisou, Tmavý Ležák"
    },
    {
      "name": "13° Hop Elixir: Superdelic, HBC 1019 & Rakau",
      "description": "4,9% alc., piv. Sibeeria, Praha, Session NEIPA"
    },
    {
      "name": "13° Protinožec",
      "description": "6% alc. piv. Volt, Jablonec nad Nisou, Australian Pale Ale"
    },
    {
      "name": "17° Tlustý Netopýr",
      "description": "7,5% alc. piv. Antoš, Slaný, Rye IPA"
    },
    {
      "name": "9° Sour Joy Gose",
      "description": "3,5% alc. piv. Upside Down, Fruit Sour Ale"
    }
  ]
}